mll/dispatcher.py
mll/forked_model.py
mll/grammar_revision.py
mll/mlltranspiler.py
mll/new_grammar_revision.py
mll/sequential_model.py
mll/simple_model.py
mll/superMLL.py
mll/testMLL.py
mll/utils.py
mll-2.1.3.dist-info/LICENSE
mll-2.1.3.dist-info/METADATA
mll-2.1.3.dist-info/WHEEL
mll-2.1.3.dist-info/top_level.txt
mll-2.1.3.dist-info/RECORD
