Metadata-Version: 2.1
Name: mll
Version: 2.1.3
Summary: A machine learning language that have a specific grammar made to simplify large and complex machine learning and deep learning tasks
Home-page: https://github.com/riccardobernardi/MLL-machine-learning-language
Author: Bernardi Riccardo
Author-email: riccardo.bernardi@rocketmail.com
License: UNKNOWN
Platform: UNKNOWN
Classifier: Programming Language :: Python :: 3
Classifier: License :: OSI Approved :: MIT License
Classifier: Operating System :: OS Independent
Requires-Dist: lark-parser
Requires-Dist: numpy
Requires-Dist: tensorflow
Requires-Dist: keras
Requires-Dist: termcolor
Requires-Dist: sklearn
Requires-Dist: mlxtend
